pytest_zafira/__init__.py
pytest_zafira/screenshot_plugin.py
pytest_zafira/zafira_plugin.py
pytest_zafira/api/__init__.py
pytest_zafira/api/api_request.py
pytest_zafira/api/client.py
pytest_zafira/api/payloads/__init__.py
pytest_zafira/api/payloads/job.py
pytest_zafira/api/payloads/project_payload.py
pytest_zafira/api/payloads/refresh_token.py
pytest_zafira/api/payloads/test.py
pytest_zafira/api/payloads/test_artifact.py
pytest_zafira/api/payloads/test_case.py
pytest_zafira/api/payloads/test_run.py
pytest_zafira/api/payloads/test_suite.py
pytest_zafira/constants/__init__.py
pytest_zafira/constants/constants.py
pytest_zafira/exceptions/__init__.py
pytest_zafira/services/__init__.py
pytest_zafira/services/amazon_service.py
pytest_zafira/services/rabbitmq_service.py
pytest_zafira/utils/__init__.py
pytest_zafira/utils/context.py
pytest_zafira/utils/driver_provider.py
pytest_zafira/utils/environ_parser.py
pytest_zafira/utils/screenshot.py
pytest_zafira-1.0.3.dist-info/LICENSE
pytest_zafira-1.0.3.dist-info/METADATA
pytest_zafira-1.0.3.dist-info/WHEEL
pytest_zafira-1.0.3.dist-info/entry_points.txt
pytest_zafira-1.0.3.dist-info/top_level.txt
pytest_zafira-1.0.3.dist-info/RECORD
