Metadata-Version: 2.1
Name: pytest-zafira
Version: 1.0.3
Summary: A Zafira plugin for pytest
Home-page: https://github.com/qaprosoft/zafira-pytest
Author: Vadim Delendik
Author-email: vdelendik@qaprosoft.com
Maintainer: Vadim Delendik
Maintainer-email: vdelendik@qaprosoft.com
License: Apache Software License 2.0
Keywords: pytest,zafira
Platform: UNKNOWN
Classifier: Development Status :: 5 - Production/Stable
Classifier: Framework :: Pytest
Classifier: Intended Audience :: Developers
Classifier: Topic :: Software Development :: Testing
Classifier: Programming Language :: Python
Classifier: Programming Language :: Python :: 2
Classifier: Programming Language :: Python :: 2.7
Classifier: Programming Language :: Python :: 3
Classifier: Programming Language :: Python :: 3.5
Classifier: Programming Language :: Python :: 3.6
Classifier: Programming Language :: Python :: 3.7
Classifier: Programming Language :: Python :: Implementation :: CPython
Classifier: Programming Language :: Python :: Implementation :: PyPy
Classifier: Operating System :: OS Independent
Classifier: License :: OSI Approved :: Apache Software License
Requires-Python: !=2.*.*, !=3.0.*, !=3.1.*, !=3.2.*, !=3.3.*, !=3.4.*
Requires-Dist: allure-python-commons (==2.5.4)
Requires-Dist: atomicwrites (==1.2.1)
Requires-Dist: attrs (==18.2.0)
Requires-Dist: boto3 (==1.9.106)
Requires-Dist: botocore (==1.12.106)
Requires-Dist: certifi (==2018.11.29)
Requires-Dist: chardet (==3.0.4)
Requires-Dist: configparser (==3.5.0)
Requires-Dist: docutils (==0.14)
Requires-Dist: idna (==2.8)
Requires-Dist: jmespath (==0.9.4)
Requires-Dist: more-itertools (==4.3.0)
Requires-Dist: pika (==1.0.1)
Requires-Dist: pluggy (==0.7.1)
Requires-Dist: py (==1.6.0)
Requires-Dist: pytest (==4.1.1)
Requires-Dist: python-dateutil (==2.8.0)
Requires-Dist: PyYAML (==3.13)
Requires-Dist: requests (==2.21.0)
Requires-Dist: s3transfer (==0.2.0)
Requires-Dist: selenium (==3.14.0)
Requires-Dist: six (==1.11.0)
Requires-Dist: urllib3 (==1.23)
